main/__init__.py
command_manager_util-0.1.1.dist-info/LICENSE
command_manager_util-0.1.1.dist-info/METADATA
command_manager_util-0.1.1.dist-info/WHEEL
command_manager_util-0.1.1.dist-info/entry_points.txt
command_manager_util-0.1.1.dist-info/top_level.txt
command_manager_util-0.1.1.dist-info/RECORD
