Metadata-Version: 2.2
Name: command-manager-util
Version: 0.1.1
Summary: This manages all the usesful commands at one place
Home-page: https://github.com/Sahaj001/Script-Manager
Author: Sahaj Pratap Singh
License: Apache 2.0
Classifier: Programming Language :: Python :: 3
Classifier: License :: OSI Approved :: Apache Software License
Classifier: Operating System :: OS Independent
Requires-Python: >=3.6
License-File: LICENSE
Dynamic: author
Dynamic: classifier
Dynamic: description
Dynamic: description-content-type
Dynamic: home-page
Dynamic: license
Dynamic: requires-python
Dynamic: summary
